pymaxspots/__init__.py
pymaxspots/lineations.py
pymaxspots/maxspots.py
pymaxspots-1.0.5.dist-info/METADATA
pymaxspots-1.0.5.dist-info/WHEEL
pymaxspots-1.0.5.dist-info/licenses/LICENSE.md
pymaxspots-1.0.5.dist-info/RECORD
