Metadata-Version: 2.4
Name: pymaxspots
Version: 1.0.5
Summary: Computing and connecting horizontal gradient maxima in potential-field geophysics
Project-URL: Homepage, https://code.usgs.gov/gmegsc/pymaxspots/
Project-URL: Issues, https://code.usgs.gov/gmegsc/pymaxspots/issues
Author-email: Collin Cronkite-Ratcliff <ccronkite-ratcliff@usgs.gov>
License: Public domain
License-File: LICENSE.md
Classifier: Operating System :: OS Independent
Classifier: Programming Language :: Python :: 3
Requires-Python: >=3.9
Requires-Dist: numba
Requires-Dist: scipy
Provides-Extra: test
Requires-Dist: geopandas; extra == 'test'
Requires-Dist: matplotlib; extra == 'test'
Requires-Dist: rasterio; extra == 'test'
